dlt/__init__.py
dlt/constants.py
dlt/exceptions.py
dlt/packet.py
dlt/payloadargument.py
dlt/reader.py
dlt/typereader.py
dlt/header/__init__.py
dlt/header/extendedheader.py
dlt/header/header.py
dlt/header/standardheader.py
dlt/header/storageheader.py
dlt/payload/__init__.py
dlt/payload/payload.py
dlt/payload/payloadnonverbose.py
dlt/payload/payloadverbose.py
dlt/services/__init__.py
dlt/services/base.py
dlt/services/getdefaultloglevel.py
dlt/services/getloginfo.py
dlt/services/getsoftwareversion.py
dlt/services/gettracestatus.py
dlt/services/resettofactorydefault.py
dlt/services/setdefaultloglevel.py
dlt/services/setdefaulttracestatus.py
dlt/services/setmessagefiltering.py
dlt/services/storeconfiguration.py
dlt/types/__init__.py
dlt/types/aray.py
dlt/types/base.py
dlt/types/bool.py
dlt/types/floa.py
dlt/types/rawd.py
dlt/types/sint.py
dlt/types/strg.py
dlt/types/stru.py
dlt/types/trai.py
dlt/types/uint.py
dltreader-0.0.2.dist-info/LICENSE
dltreader-0.0.2.dist-info/METADATA
dltreader-0.0.2.dist-info/WHEEL
dltreader-0.0.2.dist-info/top_level.txt
dltreader-0.0.2.dist-info/RECORD
