Metadata-Version: 2.1
Name: dltreader
Version: 0.0.2
Summary: DLT reader for AUTOSAR Diagnostic, Log and Trace Protocol.
Home-page: https://github.com/keans/dltreader
Author: Ansgar Kellner
Author-email: keans@gmx.de
License: MIT
Keywords: dlt
Platform: UNKNOWN
Classifier: Development Status :: 3 - Alpha
Classifier: Intended Audience :: Developers
Classifier: Topic :: Software Development :: Build Tools
Classifier: License :: OSI Approved :: MIT License
Classifier: Programming Language :: Python :: 3
Classifier: Programming Language :: Python :: 3.6
Classifier: Programming Language :: Python :: 3.7
Classifier: Programming Language :: Python :: 3.8
Classifier: Programming Language :: Python :: 3.9
Classifier: Programming Language :: Python :: 3.10
Classifier: Programming Language :: Python :: 3.11
Classifier: Programming Language :: Python :: 3.12
Requires-Python: >=3.6
License-File: LICENSE
